{
  "TranslationProperties": {
    "Name": "variants.Goldenwood_Arenberg.name"
  },
  "ItemLevel": 15,
  "MaxStack": 100,
  "Icon": "Icons/ItemsGenerated/Variants/Goldenwood_Arenberg.png",
  "Categories": [
    "Blocks.Rocks"
  ],
  "PlayerAnimationsId": "Block",
  "Set": "Goldenwood",
  "Recipe": {
    "Input": [
      {
        "ItemId": "Wood_Goldenwood_Planks",
        "Quantity": 1
      }
    ],
    "BenchRequirement": [
      {
        "Id": "YmmersiveCarpentry",
        "Type": "StructuralCrafting",
        "Categories": [
          "Goldenwood"
        ]
      }
    ],
    "OutputQuantity": 1,
    "TimeSeconds": 0
  },
  "BlockType": {
    "Material": "Solid",
    "DrawType": "Cube",
    "Group": "Wood",
    "Flags": {},
    "Gathering": {
      "Breaking": {
        "GatherType": "Rocks"
      }
    },
    "Textures": [
      {
        "All": "BlockTextures/Goldenwood_Arenberg.png",
        "Weight": 1
      }
    ],
    "BlockParticleSetId": "Wood",
    "ParticleColor": "#936a32",
    "BlockSoundSetId": "Wood"
  },
  "Tags": {
    "Type": [
      "Arenberg"
    ],
    "Family": [
      "Goldenwood"
    ]
  },
  "ItemSoundSetId": "ISS_Blocks_Wood"
}